MANIFEST.in
README.rst
setup.py
Shimehari_DebugToolbar.egg-info/PKG-INFO
Shimehari_DebugToolbar.egg-info/SOURCES.txt
Shimehari_DebugToolbar.egg-info/dependency_links.txt
Shimehari_DebugToolbar.egg-info/not-zip-safe
Shimehari_DebugToolbar.egg-info/requires.txt
Shimehari_DebugToolbar.egg-info/top_level.txt
shimehari_debugtoolbar/__init__.py
shimehari_debugtoolbar/toolbar.py
shimehari_debugtoolbar/utils.py
shimehari_debugtoolbar/helpers/__init__.py
shimehari_debugtoolbar/helpers/sqlalchemy_debug.py
shimehari_debugtoolbar/panels/__init__.py
shimehari_debugtoolbar/panels/headers.py
shimehari_debugtoolbar/panels/logger.py
shimehari_debugtoolbar/panels/profiler.py
shimehari_debugtoolbar/panels/request_vars.py
shimehari_debugtoolbar/panels/sqlalchemy.py
shimehari_debugtoolbar/panels/template.py
shimehari_debugtoolbar/panels/timer.py
shimehari_debugtoolbar/panels/versions.py
shimehari_debugtoolbar/static/codemirror/codemirror.css
shimehari_debugtoolbar/static/codemirror/codemirror.js
shimehari_debugtoolbar/static/codemirror/mode/clike/clike.js
shimehari_debugtoolbar/static/codemirror/mode/clike/index.html
shimehari_debugtoolbar/static/codemirror/mode/clojure/clojure.js
shimehari_debugtoolbar/static/codemirror/mode/clojure/index.html
shimehari_debugtoolbar/static/codemirror/mode/coffeescript/LICENSE
shimehari_debugtoolbar/static/codemirror/mode/coffeescript/coffeescript.js
shimehari_debugtoolbar/static/codemirror/mode/coffeescript/index.html
shimehari_debugtoolbar/static/codemirror/mode/css/css.js
shimehari_debugtoolbar/static/codemirror/mode/css/index.html
shimehari_debugtoolbar/static/codemirror/mode/diff/diff.css
shimehari_debugtoolbar/static/codemirror/mode/diff/diff.js
shimehari_debugtoolbar/static/codemirror/mode/diff/index.html
shimehari_debugtoolbar/static/codemirror/mode/ecl/ecl.js
shimehari_debugtoolbar/static/codemirror/mode/ecl/index.html
shimehari_debugtoolbar/static/codemirror/mode/gfm/gfm.js
shimehari_debugtoolbar/static/codemirror/mode/gfm/index.html
shimehari_debugtoolbar/static/codemirror/mode/go/go.js
shimehari_debugtoolbar/static/codemirror/mode/go/index.html
shimehari_debugtoolbar/static/codemirror/mode/groovy/groovy.js
shimehari_debugtoolbar/static/codemirror/mode/groovy/index.html
