Metadata-Version: 1.0
Name: Shimehari-DebugToolbar
Version: 0.1.1
Summary: A port of the Django debug toolbar to Shimehari
Home-page: http://github.com/matsumos/shimehari-debugtoolbar
Author: Keiichiro Matsumoto
Author-email: matsumos@gmail.com
License: BSD
Platform: any
Classifier: Development Status :: 4 - Beta
Classifier: Environment :: Web Environment
Classifier: Intended Audience :: Developers
Classifier: License :: OSI Approved :: BSD License
Classifier: Operating System :: OS Independent
Classifier: Programming Language :: Python
Classifier: Topic :: Internet :: WWW/HTTP :: Dynamic Content
Classifier: Topic :: Software Development :: Libraries :: Python Modules
